{
  "_comment": "Shared fixture format for cross-validation between kerits and KERIpy. The 'expected' fields are generated by scripts/generate-keripy-saids.py — do not edit them by hand. Version string fields use KERI10JSON000000_ as the seed value (KERIpy requires a parseable seed).",
  "fixtures": [
    {
      "id": "kel-icp",
      "description": "KERI inception event with single signing key, single next key digest, no witnesses",
      "surface": {
        "saidField": "d",
        "derivedFieldsInOrder": ["v", "t", "d", "i", "kt", "k", "nt", "n", "bt", "b"],
        "hasVersionString": true,
        "versionStringField": "v"
      },
      "artifact": {
        "v": "KERI10JSON000000_",
        "t": "icp",
        "d": "",
        "i": "",
        "kt": "1",
        "k": ["DHr0-I-mMN7h6cLMOTRJkkfPuMd0vgQPrOk4Y3edaHjr"],
        "nt": "1",
        "n": ["EIFG_uqfr1yN560LoHYHfvPAhxQ5sN6p3any8Ir7kGpq"],
        "bt": "0",
        "b": []
      }
    },
    {
      "id": "tel-vcp",
      "description": "TEL registry inception (vcp) with issuer identifier, no witnesses",
      "surface": {
        "saidField": "d",
        "derivedFieldsInOrder": ["v", "t", "d", "i", "ii", "b", "bt"],
        "hasVersionString": true,
        "versionStringField": "v"
      },
      "artifact": {
        "v": "KERI10JSON000000_",
        "t": "vcp",
        "d": "",
        "i": "",
        "ii": "EDP1vHcw_wc4M0MPoW1gVXEl3XEY2eJMBqhBMBCAFXMq",
        "b": [],
        "bt": "0"
      }
    }
  ]
}
